db.py
utils.py
wikiwall.py
wikiwall-0.2.1.dist-info/LICENSE
wikiwall-0.2.1.dist-info/METADATA
wikiwall-0.2.1.dist-info/WHEEL
wikiwall-0.2.1.dist-info/entry_points.txt
wikiwall-0.2.1.dist-info/top_level.txt
wikiwall-0.2.1.dist-info/RECORD
