Metadata-Version: 2.1
Name: wikiwall
Version: 0.2.1
Summary: Set desktop background to random Wikiart image.
Home-page: https://github.com/kylepw/wikiwall
Author: Kyle Weeks
Author-email: kylepw@gmail.com
License: MIT License
Platform: UNKNOWN
Classifier: Natural Language :: English
Classifier: Programming Language :: Python :: 3
Classifier: License :: OSI Approved :: MIT License
Classifier: Operating System :: MacOS
Requires-Dist: Click
Requires-Dist: lxml
Requires-Dist: requests
Requires-Dist: tqdm
